{
    "current": {
        "title": "THE GAMBLER",
        "artist": "DISK EYES NASHVILLE"
    },
    "recent": [
        {
            "title": "A HOUSE IS NOT A HOME",
            "artist": "Nick Manson"
        },
        {
            "title": "Thrill is Gone",
            "artist": "MANSON STRINGS"
        },
        {
            "title": "South Point",
            "artist": "Brian Withycombe"
        },
        {
            "title": "ALL FOUR SEASONS",
            "artist": "Moro-Eden"
        },
        {
            "title": "BLUE MOON",
            "artist": "John Morton"
        },
        {
            "title": "About Tonight",
            "artist": "MIRAGE BAND"
        },
        {
            "title": "Samsonite Waltz",
            "artist": "Dave Keenan"
        },
        {
            "title": "You're the Best Thing",
            "artist": "DAVE PATT"
        },
        {
            "title": "Jazz Man",
            "artist": "Harley Music"
        },
        {
            "title": "CAMILLA",
            "artist": "Jerry Cortez"
        }
    ]
}