{
    "current": {
        "title": "You're the Best Thing",
        "artist": "DAVE PATT"
    },
    "recent": [
        {
            "title": "I CAN LOVE YOU LIKE THAT",
            "artist": "TOMMY/BRIAN"
        },
        {
            "title": "HAKUNA MATATA",
            "artist": "Josephs Band"
        },
        {
            "title": "Wrong Again",
            "artist": "Frank Josephs"
        },
        {
            "title": "ALL I WANNA DO",
            "artist": "Harley"
        },
        {
            "title": "DREAMLOVER",
            "artist": "It's Lenny Moore"
        },
        {
            "title": "NEW KID IN TOWN",
            "artist": "MIRAGE BAND"
        },
        {
            "title": "I'LL NEVER STOP LOVING YOU",
            "artist": "Tom Kellock"
        },
        {
            "title": "DIXIE MOON",
            "artist": "LENNY MOORE"
        },
        {
            "title": "Hissing Of Summer Lawns",
            "artist": "Tom Politzer"
        },
        {
            "title": "IF YOU LEAVE ME NOW",
            "artist": "Daniel Ho"
        }
    ]
}