{
    "current": {
        "title": "FOR ONCE IN OUR LIVES",
        "artist": "Andre Mayeux"
    },
    "recent": [
        {
            "title": "SUNNY CAME HOME",
            "artist": "MOORE and BRENGLE"
        },
        {
            "title": "Run",
            "artist": "Los Devlin Strings"
        },
        {
            "title": "ROLL TO ME",
            "artist": "Harley Brothers"
        },
        {
            "title": "BLUE MOON",
            "artist": "John Morton"
        },
        {
            "title": "I BELIEVE IN YOU AND ME",
            "artist": "Josephs Band"
        },
        {
            "title": "DROWNING IN YOUR TEARS",
            "artist": "Funtastic Music"
        },
        {
            "title": "I JUST CAN'T LET GO",
            "artist": "FRISCO PILEDRIVERS"
        },
        {
            "title": "FEEL LIKE MAKIN' LOVE",
            "artist": "Nick Manson"
        },
        {
            "title": "I CAN'T MAKE YOU LOVE ME",
            "artist": "MIRAGE BAND"
        },
        {
            "title": "Batata Bossa",
            "artist": "Dave Keenan"
        }
    ]
}