{
    "current": {
        "title": "My Favorite Mistake",
        "artist": "Frank Josephs"
    },
    "recent": [
        {
            "title": "LET IT BE ME",
            "artist": "Josephs Band"
        },
        {
            "title": "Love's In Need Of Love Today",
            "artist": "Andy Suzuki"
        },
        {
            "title": "AWAKENING",
            "artist": "Jazz Pretenders"
        },
        {
            "title": "LITTLE MORE TIME WITH YOU",
            "artist": "Andre Mayeux"
        },
        {
            "title": "DON'T TELL ME",
            "artist": "Flyin' Hawaiian Bro"
        },
        {
            "title": "RUBY BABY",
            "artist": "Funtastic"
        },
        {
            "title": "DON'T YOU WORRY 'BOUT A THING",
            "artist": "MANSON LIVE"
        },
        {
            "title": "BAND OF GOLD",
            "artist": "Moro-Eden"
        },
        {
            "title": "QUEEN OF HEARTS",
            "artist": "TOM KELLOCK'S BTU"
        },
        {
            "title": "I Don't Want To Spoil The Party",
            "artist": "John Morton"
        }
    ]
}