{
    "current": {
        "title": "Run",
        "artist": "Los Devlin Strings"
    },
    "recent": [
        {
            "title": "ALL FOUR SEASONS",
            "artist": "Moro-Eden"
        },
        {
            "title": "A Love Song",
            "artist": "John Morton"
        },
        {
            "title": "MIDNIGHT TRAIN TO GEORGIA",
            "artist": "Daniel Ho"
        },
        {
            "title": "At the Fair",
            "artist": "Mirage Ensemble"
        },
        {
            "title": "Groovin'",
            "artist": "Harley Music"
        },
        {
            "title": "Indio",
            "artist": "Ray Kelley"
        },
        {
            "title": "I CAN LOVE YOU LIKE THAT",
            "artist": "TOMMY/BRIAN"
        },
        {
            "title": "FAIR TOMORROW",
            "artist": "Jerry Cortez"
        },
        {
            "title": "Walk On By",
            "artist": "Manson Music"
        },
        {
            "title": "I DON'T WANNA BE ALONE",
            "artist": "MOORE and BRENGLE"
        }
    ]
}