{
    "current": {
        "title": "More Than Just A Life",
        "artist": "Brian Withycombe"
    },
    "recent": [
        {
            "title": "IF WE FALL IN LOVE AGAIN",
            "artist": "Tom Kellock"
        },
        {
            "title": "After Hours",
            "artist": "Ray Kelley"
        },
        {
            "title": "You're the Best Thing",
            "artist": "DAVE PATT"
        },
        {
            "title": "YOU'RE THE INSPIRATION",
            "artist": "FRANK JOSEPHS BAND"
        },
        {
            "title": "DIAMOND DUST",
            "artist": "ANDY SUZUKI STRINGS"
        },
        {
            "title": "About Tonight",
            "artist": "MIRAGE BAND"
        },
        {
            "title": "CAPTAIN OF HER HEART",
            "artist": "ANDY SUZUKI/NICK MANSON"
        },
        {
            "title": "FOLLOW YOU, FOLLOW ME",
            "artist": "Nick Manson"
        },
        {
            "title": "Wrong Again",
            "artist": "Frank Josephs"
        },
        {
            "title": "GLAMOUR PROFESSION",
            "artist": "North Point"
        }
    ]
}