{
    "current": {
        "title": "Jazz Man",
        "artist": "Harley Music"
    },
    "recent": [
        {
            "title": "Just Like This Train",
            "artist": "San Francisco"
        },
        {
            "title": "CAMILLA",
            "artist": "Jerry Cortez"
        },
        {
            "title": "Come Fly With Me",
            "artist": "Ray Kelley"
        },
        {
            "title": "SACRIFICE",
            "artist": "MANSON/MARROW/HALL"
        },
        {
            "title": "EARTH ANGEL (WILL YOU BE MINE)",
            "artist": "MANSON STRINGS"
        },
        {
            "title": "COME GO WITH ME",
            "artist": "North Point"
        },
        {
            "title": "LOVE LETTERS",
            "artist": "MANSON LIVE"
        },
        {
            "title": "PLEASE",
            "artist": "Frank Josephs Group"
        },
        {
            "title": "BABY NOW THAT I'VE FOUND YOU",
            "artist": "STANDING PATT MUSIC"
        },
        {
            "title": "My Favorite Mistake",
            "artist": "Frank Josephs"
        }
    ]
}