{
    "current": {
        "title": "SACRIFICE",
        "artist": "MANSON/MARROW/HALL"
    },
    "recent": [
        {
            "title": "CRY ME A RIVER",
            "artist": "LENNY MOORE"
        },
        {
            "title": "Things We Do For Love",
            "artist": "Tom Politzer/S.F."
        },
        {
            "title": "MAGNOLIA",
            "artist": "Funtastic"
        },
        {
            "title": "For Elfi",
            "artist": "Nick Manson"
        },
        {
            "title": "Pickin Like Lee",
            "artist": "Michael Ranstrom"
        },
        {
            "title": "STAY (I MISSED YOU)",
            "artist": "Moro-Eden"
        },
        {
            "title": "RECOVER YOUR SOUL",
            "artist": "Politzer/Withycombe"
        },
        {
            "title": "SOUL SHADOWS",
            "artist": "TOM KELLOCK'S BTU"
        },
        {
            "title": "Always",
            "artist": "Harley Bros."
        },
        {
            "title": "CAPTAIN OF HER HEART",
            "artist": "ANDY SUZUKI/NICK MANSON"
        }
    ]
}