{
    "current": {
        "title": "YOUR'E NO GOOD",
        "artist": "FLYIN' HAWAIIN BRO"
    },
    "recent": [
        {
            "title": "NIGHT IN PARIS",
            "artist": "Ho Tones"
        },
        {
            "title": "Always Something There To Remind Me",
            "artist": "Harley"
        },
        {
            "title": "Every Breath You Take",
            "artist": "Harley Music"
        },
        {
            "title": "Soulful Strut",
            "artist": "Harley Bros."
        },
        {
            "title": "DON'T GO BREAKIN' MY HEART",
            "artist": "Devlin's Strings"
        },
        {
            "title": "DIXIE MOON",
            "artist": "LENNY MOORE"
        },
        {
            "title": "ENDLESS LOVE",
            "artist": "Daniel Ho"
        },
        {
            "title": "HAKUNA MATATA",
            "artist": "Josephs Band"
        },
        {
            "title": "STUBBORN KIND OF FELLOW",
            "artist": "Crescenta Valley Boys"
        },
        {
            "title": "THE STRANGER",
            "artist": "North Point"
        }
    ]
}